jaxip/__init__.py
jaxip/_version.py
jaxip/config.py
jaxip/logger.py
jaxip/pytree.py
jaxip/types.py
jaxip/units.py
jaxip/atoms/__init__.py
jaxip/atoms/_structure.py
jaxip/atoms/box.py
jaxip/atoms/element.py
jaxip/atoms/neighbor.py
jaxip/atoms/structure.py
jaxip/datasets/__init__.py
jaxip/datasets/dataset.py
jaxip/datasets/runner.py
jaxip/descriptors/__init__.py
jaxip/descriptors/descriptor.py
jaxip/descriptors/scaler.py
jaxip/descriptors/acsf/__init__.py
jaxip/descriptors/acsf/_acsf.py
jaxip/descriptors/acsf/acsf.py
jaxip/descriptors/acsf/angular.py
jaxip/descriptors/acsf/cutoff.py
jaxip/descriptors/acsf/radial.py
jaxip/descriptors/acsf/symmetry.py
jaxip/models/__init__.py
jaxip/models/model.py
jaxip/models/nn/__init__.py
jaxip/models/nn/activation.py
jaxip/models/nn/initializer.py
jaxip/models/nn/network.py
jaxip/potentials/__init__.py
jaxip/potentials/_energy.py
jaxip/potentials/_force.py
jaxip/potentials/atomic_potential.py
jaxip/potentials/nnp/__init__.py
jaxip/potentials/nnp/gradient_descent.py
jaxip/potentials/nnp/kalman_filter.py
jaxip/potentials/nnp/metrics.py
jaxip/potentials/nnp/nnp.py
jaxip/potentials/nnp/potential.py
jaxip/potentials/nnp/settings.py
jaxip/simulation/__init__.py
jaxip/simulation/lj.py
jaxip/simulation/mc.py
jaxip/simulation/md.py
jaxip/simulation/run.py
jaxip/simulation/thermostat.py
jaxip/utils/__init__.py
jaxip/utils/attribute.py
jaxip/utils/batch.py
jaxip/utils/compare.py
jaxip/utils/profiler.py
jaxip/utils/tokenize.py
jaxip-0.7.5.dist-info/AUTHORS.rst
jaxip-0.7.5.dist-info/LICENSE
jaxip-0.7.5.dist-info/METADATA
jaxip-0.7.5.dist-info/WHEEL
jaxip-0.7.5.dist-info/entry_points.txt
jaxip-0.7.5.dist-info/top_level.txt
jaxip-0.7.5.dist-info/RECORD
